djinit/__init__.py
djinit/index.py
djinit/utilities/__init__.py
djinit/utilities/autoopen.py
djinit/utilities/project.py
djinit/utilities/settings.py
djinit/utilities/urls.py
djinit/utilities/views.py
djinit/utilities/templates/index.html
djinit/utilities/templates/app/page.html
djinit/utilities/templates/includes/footer.html
djinit/utilities/templates/includes/header.html
djinit/utilities/templates/includes/sidebar.html
djinit/utilities/templates/layouts/base.html
djinit/utilities/templates/partials/_css.html
djinit/utilities/templates/partials/_js.html
djinit/utilities/templates/partials/_pagination.html
djinit/utilities/templates/partials/_swal.html
djinit-0.0.7.dist-info/LICENSE.txt
djinit-0.0.7.dist-info/METADATA
djinit-0.0.7.dist-info/WHEEL
djinit-0.0.7.dist-info/entry_points.txt
djinit-0.0.7.dist-info/top_level.txt
djinit-0.0.7.dist-info/RECORD
