Metadata-Version: 2.1
Name: djinit
Version: 0.0.7
Summary: Django project initialize
Home-page: https://github.com/ardevpk/djinit
Author: Abdul Rehman
Author-email: adnan1470369258@gmail.com
Project-URL: Bug Tracker, https://github.com/ardevpk/djinit/issues
Classifier: Programming Language :: Python :: 3
Classifier: License :: OSI Approved :: MIT License
Classifier: Operating System :: OS Independent
Requires-Python: >=3.6
License-File: LICENSE.txt
Requires-Dist: Django (>=3.8)
Requires-Dist: virtualenv (>=20)
